{
  "run_name": "gfn-lb0-2000.cls.random.mh.gn.free.s50",
  "config": {
    "sampler": "cls",
    "method": "random",
    "mh": true,
    "grad_norm": true,
    "oracle": false,
    "steps": 50,
    "model_path": "/mount/studenten-temp1/users/singhsk/thesis/thesis/gfn-lm-tuning/infill_subj_arithmetic/gpt2_large_sft_output",
    "model_tag": "gfn-lb0-2000",
    "peft_checkpoint": "/mount/studenten-temp1/users/singhsk/thesis/thesis/gfn-lm-tuning/infill_subj_arithmetic/outputs/2026-06-22/13-24-52/daily-resonance-15_1990.pt",
    "dtype": "float32",
    "data_file": null,
    "min_words": 10,
    "max_words": 40,
    "n_samples": 200,
    "num_masks": 1,
    "data_seed": 0,
    "eps_start": 10.5,
    "eps_end": 0.1,
    "temperature": 5.0,
    "noise_scale": 0.01,
    "wandb_project": "ctg-langevin-thesis",
    "wandb_group": "gfn-lb0-2000.cls_gn_on",
    "run_name": "gfn-lb0-2000.cls.random.mh.gn.free.s50",
    "no_wandb": false,
    "out_dir": "results_gfn",
    "overwrite": false
  },
  "n": 200,
  "accuracy": 0.0,
  "accept_rate": 18.36,
  "mean_l2": [
    2.541840406656265,
    2.5347933673858645,
    2.5361063981056216,
    2.532397527098656,
    2.530654158592224,
    2.519373964071274,
    2.517759560346603,
    2.517417824268341,
    2.510146673321724,
    2.5120668959617616,
    2.514108443260193,
    2.508920519948006,
    2.508063975572586,
    2.5112003046274185,
    2.5096885460615157,
    2.5083841890096665,
    2.506920171380043,
    2.5058636969327925,
    2.508109433054924,
    2.504947677254677,
    2.504113718867302,
    2.505223494172096,
    2.503239856362343,
    2.503530460000038,
    2.501560074090958,
    2.501560074090958,
    2.5002546256780622,
    2.4992646735906603,
    2.49916572868824,
    2.49916572868824,
    2.49916572868824,
    2.49916572868824,
    2.49916572868824,
    2.49916572868824,
    2.49916572868824,
    2.49916572868824,
    2.49916572868824,
    2.49916572868824,
    2.49916572868824,
    2.49916572868824,
    2.49916572868824,
    2.49916572868824,
    2.49916572868824,
    2.49916572868824,
    2.49916572868824,
    2.49916572868824,
    2.49916572868824,
    2.49916572868824,
    2.49916572868824,
    2.49916572868824
  ],
  "mean_kl": [
    9.552972686681896,
    9.609160715732724,
    9.699267002791167,
    9.71313217241317,
    9.856471553333103,
    9.845473867543042,
    9.977409365065396,
    10.043597408421338,
    10.07462895859033,
    10.037073689885437,
    10.103128072209657,
    10.110591390021145,
    10.087876825667918,
    10.058769333697855,
    10.088361759521067,
    10.120056045390665,
    10.069086262530472,
    10.06532710985426,
    10.056209864546837,
    9.987838484277308,
    10.031032495429098,
    10.045897207190574,
    10.04445776992041,
    10.042934318115295,
    10.009806101848662,
    10.009806101848662,
    10.023351953556121,
    10.030738792945922,
    10.092522888710082,
    10.092522888710082,
    10.092522888710082,
    10.092522888710082,
    10.092522888710082,
    10.092522888710082,
    10.092522888710082,
    10.092522888710082,
    10.092522888710082,
    10.092522888710082,
    10.092522888710082,
    10.092522888710082,
    10.092522888710082,
    10.092522888710082,
    10.092522888710082,
    10.092522888710082,
    10.092522888710082,
    10.092522888710082,
    10.092522888710082,
    10.092522888710082,
    10.092522888710082,
    10.092522888710082
  ],
  "mean_entropy": [
    0.0,
    0.0,
    0.0,
    0.0,
    0.0,
    0.0,
    0.0,
    0.0,
    0.0,
    0.0,
    0.0,
    0.0,
    0.0,
    0.0,
    0.0,
    0.0,
    0.0,
    0.0,
    0.0,
    0.0,
    0.0,
    0.0,
    0.0,
    0.0,
    0.0,
    0.0,
    0.0,
    0.0,
    0.0,
    0.0,
    0.0,
    0.0,
    0.0,
    0.0,
    0.0,
    0.0,
    0.0,
    0.0,
    0.0,
    0.0,
    0.0,
    0.0,
    0.0,
    0.0,
    0.0,
    0.0,
    0.0,
    0.0,
    0.0,
    0.0
  ],
  "examples": [
    [
      "The rostrum of H. americanus bears one or more spines on the underside, which ar",
      "The rostrRegister of H. americanus bears one or more spines on the underside, wh",
      "Register"
    ],
    [
      "The spines on the claws of H. americanus are red or red @-@ tipped, while those ",
      "The spines on the claws of H. americanus are red or redDoug-@ tipped, while thos",
      " Evan"
    ],
    [
      "The underside of the claw of H. americanus is orange or red, while that of H. ga",
      "The undersideMicrosoft the claw of H. americanus is orange or red, while that of",
      " Plymouth"
    ],
    [
      "The diet of H. gammarus mostly consists of other benthic invertebrates. These in",
      "The diet of H. gammarus mostly consists of other benthic invertebrates. These in",
      " moments"
    ],
    [
      "The three clawed lobster species Homarus gammarus, H. americanus and Nephrops no",
      "The three clawed lobster species Homarus gammarus, H. americanus and Nephrops no",
      " plantation"
    ],
    [
      "Aquaculture systems for H. gammarus are under development, and production rates ",
      "Aquac Velvet systems for H. gammarus are under development, and production rates",
      " garden"
    ],
    [
      "The common name for H. gammarus preferred by the Food and Agriculture Organizati",
      "The common name for H. gammar opens preferred by the Food and Agriculture Organi",
      " mut"
    ],
    [
      "1 East End Historic District \u2014 roughly bounded by 18th St, 11th Ave, 14th St, 14",
      "1 East End scratches District \u2014 roughly bounded by 18th St, 11th Ave, 14th St, 1",
      " scratches"
    ]
  ]
}